twts/geo.py
twts/stream.py
twts-0.1.3.dist-info/entry_points.txt
twts-0.1.3.dist-info/WHEEL
twts-0.1.3.dist-info/METADATA
twts-0.1.3.dist-info/RECORD
