Metadata-Version: 2.1
Name: twts
Version: 0.1.3
Summary: stream tweets from the terminal
Author: redraw
Author-email: redraw@sdf.org
Requires-Python: >=3.8,<4.0
Classifier: Programming Language :: Python :: 3
Classifier: Programming Language :: Python :: 3.10
Classifier: Programming Language :: Python :: 3.8
Classifier: Programming Language :: Python :: 3.9
Requires-Dist: Shapely (>=1.8.2,<2.0.0)
Requires-Dist: requests (>=2.28.0,<3.0.0)
Requires-Dist: tweepy (>=4.10.0,<5.0.0)
